<?xml version="1.0" encoding="UTF-8"?><?xml-stylesheet type='text/xsl' href='_UpgradeReport_Files/UpgradeReport.xslt'?><UpgradeLog>
<Properties><Property Name="Solution" Value="SVDMPRA">
</Property><Property Name="Solution File" Value="D:\bkp\SVDMPRA\SISTEMA E OUTROS\Codigo Fonte\SVDMPRA\SVDMPRA.sln">
</Property><Property Name="User Options File" Value="D:\bkp\SVDMPRA\SISTEMA E OUTROS\Codigo Fonte\SVDMPRA\SVDMPRA.suo">
</Property><Property Name="Date" Value="segunda-feira, 11 de julho de 2011">
</Property><Property Name="Time" Value="21:04">
</Property></Properties><Event ErrorLevel="0" Project="" Source="SVDMPRA.sln" Description="File successfully backed up as D:\bkp\SVDMPRA\SISTEMA E OUTROS\Codigo Fonte\SVDMPRA\Backup\SVDMPRA.sln">
</Event><Event ErrorLevel="0" Project="" Source="SVDMPRA.suo" Description="File successfully backed up as D:\bkp\SVDMPRA\SISTEMA E OUTROS\Codigo Fonte\SVDMPRA\Backup\SVDMPRA.suo">
</Event><Event ErrorLevel="0" Project="SVDMPRA" Source="SVDMPRA.csproj" Description="Project file successfully backed up as D:\bkp\SVDMPRA\SISTEMA E OUTROS\Codigo Fonte\SVDMPRA\Backup\SVDMPRA.csproj">
</Event><Event ErrorLevel="0" Project="SVDMPRA" Source="SVDMPRA.csproj.user" Description="Project user file successfully backed up as D:\bkp\SVDMPRA\SISTEMA E OUTROS\Codigo Fonte\SVDMPRA\Backup\SVDMPRA.csproj.user">
</Event><Event ErrorLevel="0" Project="SVDMPRA" Source="Classes\banco.cs" Description="File successfully backed up as D:\bkp\SVDMPRA\SISTEMA E OUTROS\Codigo Fonte\SVDMPRA\Backup\Classes\banco.cs">
</Event><Event ErrorLevel="0" Project="SVDMPRA" Source="Classes\RA.cs" Description="File successfully backed up as D:\bkp\SVDMPRA\SISTEMA E OUTROS\Codigo Fonte\SVDMPRA\Backup\Classes\RA.cs">
</Event><Event ErrorLevel="0" Project="SVDMPRA" Source="Cliente\frmclicad.cs" Description="File successfully backed up as D:\bkp\SVDMPRA\SISTEMA E OUTROS\Codigo Fonte\SVDMPRA\Backup\Cliente\frmclicad.cs">
</Event><Event ErrorLevel="0" Project="SVDMPRA" Source="Cliente\frmclicad.Designer.cs" Description="File successfully backed up as D:\bkp\SVDMPRA\SISTEMA E OUTROS\Codigo Fonte\SVDMPRA\Backup\Cliente\frmclicad.Designer.cs">
</Event><Event ErrorLevel="0" Project="SVDMPRA" Source="Cliente\frmclimod.cs" Description="File successfully backed up as D:\bkp\SVDMPRA\SISTEMA E OUTROS\Codigo Fonte\SVDMPRA\Backup\Cliente\frmclimod.cs">
</Event><Event ErrorLevel="0" Project="SVDMPRA" Source="Cliente\frmclimod.Designer.cs" Description="File successfully backed up as D:\bkp\SVDMPRA\SISTEMA E OUTROS\Codigo Fonte\SVDMPRA\Backup\Cliente\frmclimod.Designer.cs">
</Event><Event ErrorLevel="0" Project="SVDMPRA" Source="Geracao3d\Form1.cs" Description="File successfully backed up as D:\bkp\SVDMPRA\SISTEMA E OUTROS\Codigo Fonte\SVDMPRA\Backup\Geracao3d\Form1.cs">
</Event><Event ErrorLevel="0" Project="SVDMPRA" Source="Geracao3d\Form1.Designer.cs" Description="File successfully backed up as D:\bkp\SVDMPRA\SISTEMA E OUTROS\Codigo Fonte\SVDMPRA\Backup\Geracao3d\Form1.Designer.cs">
</Event><Event ErrorLevel="0" Project="SVDMPRA" Source="Geracao3d\Form2.cs" Description="File successfully backed up as D:\bkp\SVDMPRA\SISTEMA E OUTROS\Codigo Fonte\SVDMPRA\Backup\Geracao3d\Form2.cs">
</Event><Event ErrorLevel="0" Project="SVDMPRA" Source="Geracao3d\Form2.Designer.cs" Description="File successfully backed up as D:\bkp\SVDMPRA\SISTEMA E OUTROS\Codigo Fonte\SVDMPRA\Backup\Geracao3d\Form2.Designer.cs">
</Event><Event ErrorLevel="0" Project="SVDMPRA" Source="Geracao3d\Form3.cs" Description="File successfully backed up as D:\bkp\SVDMPRA\SISTEMA E OUTROS\Codigo Fonte\SVDMPRA\Backup\Geracao3d\Form3.cs">
</Event><Event ErrorLevel="0" Project="SVDMPRA" Source="Geracao3d\Form3.Designer.cs" Description="File successfully backed up as D:\bkp\SVDMPRA\SISTEMA E OUTROS\Codigo Fonte\SVDMPRA\Backup\Geracao3d\Form3.Designer.cs">
</Event><Event ErrorLevel="0" Project="SVDMPRA" Source="Geracao3d\frmnomeset.cs" Description="File successfully backed up as D:\bkp\SVDMPRA\SISTEMA E OUTROS\Codigo Fonte\SVDMPRA\Backup\Geracao3d\frmnomeset.cs">
</Event><Event ErrorLevel="0" Project="SVDMPRA" Source="Geracao3d\frmnomeset.Designer.cs" Description="File successfully backed up as D:\bkp\SVDMPRA\SISTEMA E OUTROS\Codigo Fonte\SVDMPRA\Backup\Geracao3d\frmnomeset.Designer.cs">
</Event><Event ErrorLevel="0" Project="SVDMPRA" Source="Imoveis\frmmodimo.cs" Description="File successfully backed up as D:\bkp\SVDMPRA\SISTEMA E OUTROS\Codigo Fonte\SVDMPRA\Backup\Imoveis\frmmodimo.cs">
</Event><Event ErrorLevel="0" Project="SVDMPRA" Source="Imoveis\frmmodimo.Designer.cs" Description="File successfully backed up as D:\bkp\SVDMPRA\SISTEMA E OUTROS\Codigo Fonte\SVDMPRA\Backup\Imoveis\frmmodimo.Designer.cs">
</Event><Event ErrorLevel="0" Project="SVDMPRA" Source="Imoveis\frmaltim.cs" Description="File successfully backed up as D:\bkp\SVDMPRA\SISTEMA E OUTROS\Codigo Fonte\SVDMPRA\Backup\Imoveis\frmaltim.cs">
</Event><Event ErrorLevel="0" Project="SVDMPRA" Source="Imoveis\frmaltim.Designer.cs" Description="File successfully backed up as D:\bkp\SVDMPRA\SISTEMA E OUTROS\Codigo Fonte\SVDMPRA\Backup\Imoveis\frmaltim.Designer.cs">
</Event><Event ErrorLevel="0" Project="SVDMPRA" Source="Imoveis\frmcadim.cs" Description="File successfully backed up as D:\bkp\SVDMPRA\SISTEMA E OUTROS\Codigo Fonte\SVDMPRA\Backup\Imoveis\frmcadim.cs">
</Event><Event ErrorLevel="0" Project="SVDMPRA" Source="Imoveis\frmcadim.Designer.cs" Description="File successfully backed up as D:\bkp\SVDMPRA\SISTEMA E OUTROS\Codigo Fonte\SVDMPRA\Backup\Imoveis\frmcadim.Designer.cs">
</Event><Event ErrorLevel="0" Project="SVDMPRA" Source="Janela Login\Login.cs" Description="File successfully backed up as D:\bkp\SVDMPRA\SISTEMA E OUTROS\Codigo Fonte\SVDMPRA\Backup\Janela Login\Login.cs">
</Event><Event ErrorLevel="0" Project="SVDMPRA" Source="Janela Login\Login.Designer.cs" Description="File successfully backed up as D:\bkp\SVDMPRA\SISTEMA E OUTROS\Codigo Fonte\SVDMPRA\Backup\Janela Login\Login.Designer.cs">
</Event><Event ErrorLevel="0" Project="SVDMPRA" Source="Janela Login\Program.cs" Description="File successfully backed up as D:\bkp\SVDMPRA\SISTEMA E OUTROS\Codigo Fonte\SVDMPRA\Backup\Janela Login\Program.cs">
</Event><Event ErrorLevel="0" Project="SVDMPRA" Source="Marcadores\cadmarc.cs" Description="File successfully backed up as D:\bkp\SVDMPRA\SISTEMA E OUTROS\Codigo Fonte\SVDMPRA\Backup\Marcadores\cadmarc.cs">
</Event><Event ErrorLevel="0" Project="SVDMPRA" Source="Marcadores\cadmarc.Designer.cs" Description="File successfully backed up as D:\bkp\SVDMPRA\SISTEMA E OUTROS\Codigo Fonte\SVDMPRA\Backup\Marcadores\cadmarc.Designer.cs">
</Event><Event ErrorLevel="0" Project="SVDMPRA" Source="Marcadores\consulmark.cs" Description="File successfully backed up as D:\bkp\SVDMPRA\SISTEMA E OUTROS\Codigo Fonte\SVDMPRA\Backup\Marcadores\consulmark.cs">
</Event><Event ErrorLevel="0" Project="SVDMPRA" Source="Marcadores\consulmark.Designer.cs" Description="File successfully backed up as D:\bkp\SVDMPRA\SISTEMA E OUTROS\Codigo Fonte\SVDMPRA\Backup\Marcadores\consulmark.Designer.cs">
</Event><Event ErrorLevel="0" Project="SVDMPRA" Source="Menu Principal\principal.cs" Description="File successfully backed up as D:\bkp\SVDMPRA\SISTEMA E OUTROS\Codigo Fonte\SVDMPRA\Backup\Menu Principal\principal.cs">
</Event><Event ErrorLevel="0" Project="SVDMPRA" Source="Menu Principal\principal.Designer.cs" Description="File successfully backed up as D:\bkp\SVDMPRA\SISTEMA E OUTROS\Codigo Fonte\SVDMPRA\Backup\Menu Principal\principal.Designer.cs">
</Event><Event ErrorLevel="0" Project="SVDMPRA" Source="Móveis\frmcadmov2.cs" Description="File successfully backed up as D:\bkp\SVDMPRA\SISTEMA E OUTROS\Codigo Fonte\SVDMPRA\Backup\Móveis\frmcadmov2.cs">
</Event><Event ErrorLevel="0" Project="SVDMPRA" Source="Móveis\frmcadmov2.Designer.cs" Description="File successfully backed up as D:\bkp\SVDMPRA\SISTEMA E OUTROS\Codigo Fonte\SVDMPRA\Backup\Móveis\frmcadmov2.Designer.cs">
</Event><Event ErrorLevel="0" Project="SVDMPRA" Source="Móveis\frmmodmov.cs" Description="File successfully backed up as D:\bkp\SVDMPRA\SISTEMA E OUTROS\Codigo Fonte\SVDMPRA\Backup\Móveis\frmmodmov.cs">
</Event><Event ErrorLevel="0" Project="SVDMPRA" Source="Móveis\frmmodmov.Designer.cs" Description="File successfully backed up as D:\bkp\SVDMPRA\SISTEMA E OUTROS\Codigo Fonte\SVDMPRA\Backup\Móveis\frmmodmov.Designer.cs">
</Event><Event ErrorLevel="0" Project="SVDMPRA" Source="Móveis\frmmovcons.cs" Description="File successfully backed up as D:\bkp\SVDMPRA\SISTEMA E OUTROS\Codigo Fonte\SVDMPRA\Backup\Móveis\frmmovcons.cs">
</Event><Event ErrorLevel="0" Project="SVDMPRA" Source="Móveis\frmmovcons.Designer.cs" Description="File successfully backed up as D:\bkp\SVDMPRA\SISTEMA E OUTROS\Codigo Fonte\SVDMPRA\Backup\Móveis\frmmovcons.Designer.cs">
</Event><Event ErrorLevel="0" Project="SVDMPRA" Source="Planta\Frmconpla.cs" Description="File successfully backed up as D:\bkp\SVDMPRA\SISTEMA E OUTROS\Codigo Fonte\SVDMPRA\Backup\Planta\Frmconpla.cs">
</Event><Event ErrorLevel="0" Project="SVDMPRA" Source="Planta\Frmconpla.Designer.cs" Description="File successfully backed up as D:\bkp\SVDMPRA\SISTEMA E OUTROS\Codigo Fonte\SVDMPRA\Backup\Planta\Frmconpla.Designer.cs">
</Event><Event ErrorLevel="0" Project="SVDMPRA" Source="Planta\frmmodpla.cs" Description="File successfully backed up as D:\bkp\SVDMPRA\SISTEMA E OUTROS\Codigo Fonte\SVDMPRA\Backup\Planta\frmmodpla.cs">
</Event><Event ErrorLevel="0" Project="SVDMPRA" Source="Planta\frmmodpla.Designer.cs" Description="File successfully backed up as D:\bkp\SVDMPRA\SISTEMA E OUTROS\Codigo Fonte\SVDMPRA\Backup\Planta\frmmodpla.Designer.cs">
</Event><Event ErrorLevel="0" Project="SVDMPRA" Source="Planta\frmplancad.cs" Description="File successfully backed up as D:\bkp\SVDMPRA\SISTEMA E OUTROS\Codigo Fonte\SVDMPRA\Backup\Planta\frmplancad.cs">
</Event><Event ErrorLevel="0" Project="SVDMPRA" Source="Planta\frmplancad.Designer.cs" Description="File successfully backed up as D:\bkp\SVDMPRA\SISTEMA E OUTROS\Codigo Fonte\SVDMPRA\Backup\Planta\frmplancad.Designer.cs">
</Event><Event ErrorLevel="0" Project="SVDMPRA" Source="Properties\AssemblyInfo.cs" Description="File successfully backed up as D:\bkp\SVDMPRA\SISTEMA E OUTROS\Codigo Fonte\SVDMPRA\Backup\Properties\AssemblyInfo.cs">
</Event><Event ErrorLevel="0" Project="SVDMPRA" Source="Properties\Resources.Designer.cs" Description="File successfully backed up as D:\bkp\SVDMPRA\SISTEMA E OUTROS\Codigo Fonte\SVDMPRA\Backup\Properties\Resources.Designer.cs">
</Event><Event ErrorLevel="0" Project="SVDMPRA" Source="Properties\Settings.Designer.cs" Description="File successfully backed up as D:\bkp\SVDMPRA\SISTEMA E OUTROS\Codigo Fonte\SVDMPRA\Backup\Properties\Settings.Designer.cs">
</Event><Event ErrorLevel="0" Project="SVDMPRA" Source="Cliente\frmclicon.cs" Description="File successfully backed up as D:\bkp\SVDMPRA\SISTEMA E OUTROS\Codigo Fonte\SVDMPRA\Backup\Cliente\frmclicon.cs">
</Event><Event ErrorLevel="0" Project="SVDMPRA" Source="Cliente\frmclicon.Designer.cs" Description="File successfully backed up as D:\bkp\SVDMPRA\SISTEMA E OUTROS\Codigo Fonte\SVDMPRA\Backup\Cliente\frmclicon.Designer.cs">
</Event><Event ErrorLevel="0" Project="SVDMPRA" Source="SVDPMRADataSet.Designer.cs" Description="File successfully backed up as D:\bkp\SVDMPRA\SISTEMA E OUTROS\Codigo Fonte\SVDMPRA\Backup\SVDPMRADataSet.Designer.cs">
</Event><Event ErrorLevel="0" Project="SVDMPRA" Source="SVDPMRADataSet1.Designer.cs" Description="File successfully backed up as D:\bkp\SVDMPRA\SISTEMA E OUTROS\Codigo Fonte\SVDMPRA\Backup\SVDPMRADataSet1.Designer.cs">
</Event><Event ErrorLevel="0" Project="SVDMPRA" Source="SVDPMRADataSet10.Designer.cs" Description="File successfully backed up as D:\bkp\SVDMPRA\SISTEMA E OUTROS\Codigo Fonte\SVDMPRA\Backup\SVDPMRADataSet10.Designer.cs">
</Event><Event ErrorLevel="0" Project="SVDMPRA" Source="SVDPMRADataSet11.Designer.cs" Description="File successfully backed up as D:\bkp\SVDMPRA\SISTEMA E OUTROS\Codigo Fonte\SVDMPRA\Backup\SVDPMRADataSet11.Designer.cs">
</Event><Event ErrorLevel="0" Project="SVDMPRA" Source="SVDPMRADataSet12.Designer.cs" Description="File successfully backed up as D:\bkp\SVDMPRA\SISTEMA E OUTROS\Codigo Fonte\SVDMPRA\Backup\SVDPMRADataSet12.Designer.cs">
</Event><Event ErrorLevel="0" Project="SVDMPRA" Source="SVDPMRADataSet13.Designer.cs" Description="File successfully backed up as D:\bkp\SVDMPRA\SISTEMA E OUTROS\Codigo Fonte\SVDMPRA\Backup\SVDPMRADataSet13.Designer.cs">
</Event><Event ErrorLevel="0" Project="SVDMPRA" Source="SVDPMRADataSet2.Designer.cs" Description="File successfully backed up as D:\bkp\SVDMPRA\SISTEMA E OUTROS\Codigo Fonte\SVDMPRA\Backup\SVDPMRADataSet2.Designer.cs">
</Event><Event ErrorLevel="0" Project="SVDMPRA" Source="SVDPMRADataSet3.Designer.cs" Description="File successfully backed up as D:\bkp\SVDMPRA\SISTEMA E OUTROS\Codigo Fonte\SVDMPRA\Backup\SVDPMRADataSet3.Designer.cs">
</Event><Event ErrorLevel="0" Project="SVDMPRA" Source="SVDPMRADataSet4.Designer.cs" Description="File successfully backed up as D:\bkp\SVDMPRA\SISTEMA E OUTROS\Codigo Fonte\SVDMPRA\Backup\SVDPMRADataSet4.Designer.cs">
</Event><Event ErrorLevel="0" Project="SVDMPRA" Source="SVDPMRADataSet5.Designer.cs" Description="File successfully backed up as D:\bkp\SVDMPRA\SISTEMA E OUTROS\Codigo Fonte\SVDMPRA\Backup\SVDPMRADataSet5.Designer.cs">
</Event><Event ErrorLevel="0" Project="SVDMPRA" Source="SVDPMRADataSet6.cs" Description="File successfully backed up as D:\bkp\SVDMPRA\SISTEMA E OUTROS\Codigo Fonte\SVDMPRA\Backup\SVDPMRADataSet6.cs">
</Event><Event ErrorLevel="0" Project="SVDMPRA" Source="SVDPMRADataSet6.Designer.cs" Description="File successfully backed up as D:\bkp\SVDMPRA\SISTEMA E OUTROS\Codigo Fonte\SVDMPRA\Backup\SVDPMRADataSet6.Designer.cs">
</Event><Event ErrorLevel="0" Project="SVDMPRA" Source="SVDPMRADataSet7.Designer.cs" Description="File successfully backed up as D:\bkp\SVDMPRA\SISTEMA E OUTROS\Codigo Fonte\SVDMPRA\Backup\SVDPMRADataSet7.Designer.cs">
</Event><Event ErrorLevel="0" Project="SVDMPRA" Source="SVDPMRADataSet8.Designer.cs" Description="File successfully backed up as D:\bkp\SVDMPRA\SISTEMA E OUTROS\Codigo Fonte\SVDMPRA\Backup\SVDPMRADataSet8.Designer.cs">
</Event><Event ErrorLevel="0" Project="SVDMPRA" Source="SVDPMRADataSet9.Designer.cs" Description="File successfully backed up as D:\bkp\SVDMPRA\SISTEMA E OUTROS\Codigo Fonte\SVDMPRA\Backup\SVDPMRADataSet9.Designer.cs">
</Event><Event ErrorLevel="0" Project="SVDMPRA" Source="app.config" Description="File successfully backed up as D:\bkp\SVDMPRA\SISTEMA E OUTROS\Codigo Fonte\SVDMPRA\Backup\app.config">
</Event><Event ErrorLevel="0" Project="SVDMPRA" Source="Properties\Settings.settings" Description="File successfully backed up as D:\bkp\SVDMPRA\SISTEMA E OUTROS\Codigo Fonte\SVDMPRA\Backup\Properties\Settings.settings">
</Event><Event ErrorLevel="0" Project="SVDMPRA" Source="SVDPMRADataSet.xsc" Description="File successfully backed up as D:\bkp\SVDMPRA\SISTEMA E OUTROS\Codigo Fonte\SVDMPRA\Backup\SVDPMRADataSet.xsc">
</Event><Event ErrorLevel="0" Project="SVDMPRA" Source="SVDPMRADataSet.xsd" Description="File successfully backed up as D:\bkp\SVDMPRA\SISTEMA E OUTROS\Codigo Fonte\SVDMPRA\Backup\SVDPMRADataSet.xsd">
</Event><Event ErrorLevel="0" Project="SVDMPRA" Source="SVDPMRADataSet.xss" Description="File successfully backed up as D:\bkp\SVDMPRA\SISTEMA E OUTROS\Codigo Fonte\SVDMPRA\Backup\SVDPMRADataSet.xss">
</Event><Event ErrorLevel="0" Project="SVDMPRA" Source="SVDPMRADataSet1.xsc" Description="File successfully backed up as D:\bkp\SVDMPRA\SISTEMA E OUTROS\Codigo Fonte\SVDMPRA\Backup\SVDPMRADataSet1.xsc">
</Event><Event ErrorLevel="0" Project="SVDMPRA" Source="SVDPMRADataSet1.xsd" Description="File successfully backed up as D:\bkp\SVDMPRA\SISTEMA E OUTROS\Codigo Fonte\SVDMPRA\Backup\SVDPMRADataSet1.xsd">
</Event><Event ErrorLevel="0" Project="SVDMPRA" Source="SVDPMRADataSet1.xss" Description="File successfully backed up as D:\bkp\SVDMPRA\SISTEMA E OUTROS\Codigo Fonte\SVDMPRA\Backup\SVDPMRADataSet1.xss">
</Event><Event ErrorLevel="0" Project="SVDMPRA" Source="SVDPMRADataSet2.xsc" Description="File successfully backed up as D:\bkp\SVDMPRA\SISTEMA E OUTROS\Codigo Fonte\SVDMPRA\Backup\SVDPMRADataSet2.xsc">
</Event><Event ErrorLevel="0" Project="SVDMPRA" Source="SVDPMRADataSet2.xsd" Description="File successfully backed up as D:\bkp\SVDMPRA\SISTEMA E OUTROS\Codigo Fonte\SVDMPRA\Backup\SVDPMRADataSet2.xsd">
</Event><Event ErrorLevel="0" Project="SVDMPRA" Source="SVDPMRADataSet2.xss" Description="File successfully backed up as D:\bkp\SVDMPRA\SISTEMA E OUTROS\Codigo Fonte\SVDMPRA\Backup\SVDPMRADataSet2.xss">
</Event><Event ErrorLevel="0" Project="SVDMPRA" Source="SVDPMRADataSet3.xsc" Description="File successfully backed up as D:\bkp\SVDMPRA\SISTEMA E OUTROS\Codigo Fonte\SVDMPRA\Backup\SVDPMRADataSet3.xsc">
</Event><Event ErrorLevel="0" Project="SVDMPRA" Source="SVDPMRADataSet3.xsd" Description="File successfully backed up as D:\bkp\SVDMPRA\SISTEMA E OUTROS\Codigo Fonte\SVDMPRA\Backup\SVDPMRADataSet3.xsd">
</Event><Event ErrorLevel="0" Project="SVDMPRA" Source="SVDPMRADataSet3.xss" Description="File successfully backed up as D:\bkp\SVDMPRA\SISTEMA E OUTROS\Codigo Fonte\SVDMPRA\Backup\SVDPMRADataSet3.xss">
</Event><Event ErrorLevel="0" Project="SVDMPRA" Source="SVDPMRADataSet4.xsc" Description="File successfully backed up as D:\bkp\SVDMPRA\SISTEMA E OUTROS\Codigo Fonte\SVDMPRA\Backup\SVDPMRADataSet4.xsc">
</Event><Event ErrorLevel="0" Project="SVDMPRA" Source="SVDPMRADataSet4.xsd" Description="File successfully backed up as D:\bkp\SVDMPRA\SISTEMA E OUTROS\Codigo Fonte\SVDMPRA\Backup\SVDPMRADataSet4.xsd">
</Event><Event ErrorLevel="0" Project="SVDMPRA" Source="SVDPMRADataSet4.xss" Description="File successfully backed up as D:\bkp\SVDMPRA\SISTEMA E OUTROS\Codigo Fonte\SVDMPRA\Backup\SVDPMRADataSet4.xss">
</Event><Event ErrorLevel="0" Project="SVDMPRA" Source="SVDPMRADataSet5.xsc" Description="File successfully backed up as D:\bkp\SVDMPRA\SISTEMA E OUTROS\Codigo Fonte\SVDMPRA\Backup\SVDPMRADataSet5.xsc">
</Event><Event ErrorLevel="0" Project="SVDMPRA" Source="SVDPMRADataSet5.xsd" Description="File successfully backed up as D:\bkp\SVDMPRA\SISTEMA E OUTROS\Codigo Fonte\SVDMPRA\Backup\SVDPMRADataSet5.xsd">
</Event><Event ErrorLevel="0" Project="SVDMPRA" Source="SVDPMRADataSet5.xss" Description="File successfully backed up as D:\bkp\SVDMPRA\SISTEMA E OUTROS\Codigo Fonte\SVDMPRA\Backup\SVDPMRADataSet5.xss">
</Event><Event ErrorLevel="0" Project="SVDMPRA" Source="ClassDiagram1.cd" Description="File successfully backed up as D:\bkp\SVDMPRA\SISTEMA E OUTROS\Codigo Fonte\SVDMPRA\Backup\ClassDiagram1.cd">
</Event><Event ErrorLevel="0" Project="SVDMPRA" Source="Resources\marcador.gif" Description="File successfully backed up as D:\bkp\SVDMPRA\SISTEMA E OUTROS\Codigo Fonte\SVDMPRA\Backup\Resources\marcador.gif">
</Event><Event ErrorLevel="0" Project="SVDMPRA" Source="SVDPMRADataSet6.xsc" Description="File successfully backed up as D:\bkp\SVDMPRA\SISTEMA E OUTROS\Codigo Fonte\SVDMPRA\Backup\SVDPMRADataSet6.xsc">
</Event><Event ErrorLevel="0" Project="SVDMPRA" Source="SVDPMRADataSet6.xsd" Description="File successfully backed up as D:\bkp\SVDMPRA\SISTEMA E OUTROS\Codigo Fonte\SVDMPRA\Backup\SVDPMRADataSet6.xsd">
</Event><Event ErrorLevel="0" Project="SVDMPRA" Source="SVDPMRADataSet6.xss" Description="File successfully backed up as D:\bkp\SVDMPRA\SISTEMA E OUTROS\Codigo Fonte\SVDMPRA\Backup\SVDPMRADataSet6.xss">
</Event><Event ErrorLevel="0" Project="SVDMPRA" Source="SVDPMRADataSet7.xsc" Description="File successfully backed up as D:\bkp\SVDMPRA\SISTEMA E OUTROS\Codigo Fonte\SVDMPRA\Backup\SVDPMRADataSet7.xsc">
</Event><Event ErrorLevel="0" Project="SVDMPRA" Source="SVDPMRADataSet7.xsd" Description="File successfully backed up as D:\bkp\SVDMPRA\SISTEMA E OUTROS\Codigo Fonte\SVDMPRA\Backup\SVDPMRADataSet7.xsd">
</Event><Event ErrorLevel="0" Project="SVDMPRA" Source="SVDPMRADataSet7.xss" Description="File successfully backed up as D:\bkp\SVDMPRA\SISTEMA E OUTROS\Codigo Fonte\SVDMPRA\Backup\SVDPMRADataSet7.xss">
</Event><Event ErrorLevel="0" Project="SVDMPRA" Source="Resources\semimagen.jpg" Description="File successfully backed up as D:\bkp\SVDMPRA\SISTEMA E OUTROS\Codigo Fonte\SVDMPRA\Backup\Resources\semimagen.jpg">
</Event><Event ErrorLevel="0" Project="SVDMPRA" Source="SVDPMRADataSet10.xsc" Description="File successfully backed up as D:\bkp\SVDMPRA\SISTEMA E OUTROS\Codigo Fonte\SVDMPRA\Backup\SVDPMRADataSet10.xsc">
</Event><Event ErrorLevel="0" Project="SVDMPRA" Source="SVDPMRADataSet10.xsd" Description="File successfully backed up as D:\bkp\SVDMPRA\SISTEMA E OUTROS\Codigo Fonte\SVDMPRA\Backup\SVDPMRADataSet10.xsd">
</Event><Event ErrorLevel="0" Project="SVDMPRA" Source="SVDPMRADataSet10.xss" Description="File successfully backed up as D:\bkp\SVDMPRA\SISTEMA E OUTROS\Codigo Fonte\SVDMPRA\Backup\SVDPMRADataSet10.xss">
</Event><Event ErrorLevel="0" Project="SVDMPRA" Source="SVDPMRADataSet11.xsc" Description="File successfully backed up as D:\bkp\SVDMPRA\SISTEMA E OUTROS\Codigo Fonte\SVDMPRA\Backup\SVDPMRADataSet11.xsc">
</Event><Event ErrorLevel="0" Project="SVDMPRA" Source="SVDPMRADataSet11.xsd" Description="File successfully backed up as D:\bkp\SVDMPRA\SISTEMA E OUTROS\Codigo Fonte\SVDMPRA\Backup\SVDPMRADataSet11.xsd">
</Event><Event ErrorLevel="0" Project="SVDMPRA" Source="SVDPMRADataSet11.xss" Description="File successfully backed up as D:\bkp\SVDMPRA\SISTEMA E OUTROS\Codigo Fonte\SVDMPRA\Backup\SVDPMRADataSet11.xss">
</Event><Event ErrorLevel="0" Project="SVDMPRA" Source="SVDPMRADataSet8.xsc" Description="File successfully backed up as D:\bkp\SVDMPRA\SISTEMA E OUTROS\Codigo Fonte\SVDMPRA\Backup\SVDPMRADataSet8.xsc">
</Event><Event ErrorLevel="0" Project="SVDMPRA" Source="SVDPMRADataSet8.xsd" Description="File successfully backed up as D:\bkp\SVDMPRA\SISTEMA E OUTROS\Codigo Fonte\SVDMPRA\Backup\SVDPMRADataSet8.xsd">
</Event><Event ErrorLevel="0" Project="SVDMPRA" Source="SVDPMRADataSet8.xss" Description="File successfully backed up as D:\bkp\SVDMPRA\SISTEMA E OUTROS\Codigo Fonte\SVDMPRA\Backup\SVDPMRADataSet8.xss">
</Event><Event ErrorLevel="0" Project="SVDMPRA" Source="SVDPMRADataSet9.xsc" Description="File successfully backed up as D:\bkp\SVDMPRA\SISTEMA E OUTROS\Codigo Fonte\SVDMPRA\Backup\SVDPMRADataSet9.xsc">
</Event><Event ErrorLevel="0" Project="SVDMPRA" Source="SVDPMRADataSet9.xsd" Description="File successfully backed up as D:\bkp\SVDMPRA\SISTEMA E OUTROS\Codigo Fonte\SVDMPRA\Backup\SVDPMRADataSet9.xsd">
</Event><Event ErrorLevel="0" Project="SVDMPRA" Source="SVDPMRADataSet9.xss" Description="File successfully backed up as D:\bkp\SVDMPRA\SISTEMA E OUTROS\Codigo Fonte\SVDMPRA\Backup\SVDPMRADataSet9.xss">
</Event><Event ErrorLevel="0" Project="SVDMPRA" Source="Resources\LOGO2.jpg" Description="File successfully backed up as D:\bkp\SVDMPRA\SISTEMA E OUTROS\Codigo Fonte\SVDMPRA\Backup\Resources\LOGO2.jpg">
</Event><Event ErrorLevel="0" Project="SVDMPRA" Source="Resources\PNG_transparency_demonstration_2.png" Description="File successfully backed up as D:\bkp\SVDMPRA\SISTEMA E OUTROS\Codigo Fonte\SVDMPRA\Backup\Resources\PNG_transparency_demonstration_2.png">
</Event><Event ErrorLevel="0" Project="SVDMPRA" Source="Resources\Clients-icon.png" Description="File successfully backed up as D:\bkp\SVDMPRA\SISTEMA E OUTROS\Codigo Fonte\SVDMPRA\Backup\Resources\Clients-icon.png">
</Event><Event ErrorLevel="0" Project="SVDMPRA" Source="Resources\Ico_casa.png" Description="File successfully backed up as D:\bkp\SVDMPRA\SISTEMA E OUTROS\Codigo Fonte\SVDMPRA\Backup\Resources\Ico_casa.png">
</Event><Event ErrorLevel="0" Project="SVDMPRA" Source="Resources\home-furniture-1.2m-2007-tp_9210659475270624290.png" Description="File successfully backed up as D:\bkp\SVDMPRA\SISTEMA E OUTROS\Codigo Fonte\SVDMPRA\Backup\Resources\home-furniture-1.2m-2007-tp_9210659475270624290.png">
</Event><Event ErrorLevel="0" Project="SVDMPRA" Source="Resources\rustic-pine-bedroom-furniture-tp_5218944627483942673.png" Description="File successfully backed up as D:\bkp\SVDMPRA\SISTEMA E OUTROS\Codigo Fonte\SVDMPRA\Backup\Resources\rustic-pine-bedroom-furniture-tp_5218944627483942673.png">
</Event><Event ErrorLevel="0" Project="SVDMPRA" Source="Resources\file-manager.png" Description="File successfully backed up as D:\bkp\SVDMPRA\SISTEMA E OUTROS\Codigo Fonte\SVDMPRA\Backup\Resources\file-manager.png">
</Event><Event ErrorLevel="0" Project="SVDMPRA" Source="Resources\pattern-x.png" Description="File successfully backed up as D:\bkp\SVDMPRA\SISTEMA E OUTROS\Codigo Fonte\SVDMPRA\Backup\Resources\pattern-x.png">
</Event><Event ErrorLevel="0" Project="SVDMPRA" Source="Resources\QR-Code.png" Description="File successfully backed up as D:\bkp\SVDMPRA\SISTEMA E OUTROS\Codigo Fonte\SVDMPRA\Backup\Resources\QR-Code.png">
</Event><Event ErrorLevel="0" Project="SVDMPRA" Source="Resources\01_PH_depois.jpg" Description="File successfully backed up as D:\bkp\SVDMPRA\SISTEMA E OUTROS\Codigo Fonte\SVDMPRA\Backup\Resources\01_PH_depois.jpg">
</Event><Event ErrorLevel="0" Project="SVDMPRA" Source="Resources\altavista-ap-01.png" Description="File successfully backed up as D:\bkp\SVDMPRA\SISTEMA E OUTROS\Codigo Fonte\SVDMPRA\Backup\Resources\altavista-ap-01.png">
</Event><Event ErrorLevel="0" Project="SVDMPRA" Source="Resources\planta_rc.png" Description="File successfully backed up as D:\bkp\SVDMPRA\SISTEMA E OUTROS\Codigo Fonte\SVDMPRA\Backup\Resources\planta_rc.png">
</Event><Event ErrorLevel="0" Project="SVDMPRA" Source="Resources\estante.png" Description="File successfully backed up as D:\bkp\SVDMPRA\SISTEMA E OUTROS\Codigo Fonte\SVDMPRA\Backup\Resources\estante.png">
</Event><Event ErrorLevel="0" Project="SVDMPRA" Source="Resources\AndARScreenshot1282817273178_0.png" Description="File successfully backed up as D:\bkp\SVDMPRA\SISTEMA E OUTROS\Codigo Fonte\SVDMPRA\Backup\Resources\AndARScreenshot1282817273178_0.png">
</Event><Event ErrorLevel="0" Project="SVDMPRA" Source="Resources\icone_clientes.png" Description="File successfully backed up as D:\bkp\SVDMPRA\SISTEMA E OUTROS\Codigo Fonte\SVDMPRA\Backup\Resources\icone_clientes.png">
</Event><Event ErrorLevel="0" Project="SVDMPRA" Source="Resources\outros_4416_zip_512.png" Description="File successfully backed up as D:\bkp\SVDMPRA\SISTEMA E OUTROS\Codigo Fonte\SVDMPRA\Backup\Resources\outros_4416_zip_512.png">
</Event><Event ErrorLevel="0" Project="SVDMPRA" Source="Resources\LOGO21.jpg" Description="File successfully backed up as D:\bkp\SVDMPRA\SISTEMA E OUTROS\Codigo Fonte\SVDMPRA\Backup\Resources\LOGO21.jpg">
</Event><Event ErrorLevel="0" Project="SVDMPRA" Source="SVDPMRADataSet12.xsc" Description="File successfully backed up as D:\bkp\SVDMPRA\SISTEMA E OUTROS\Codigo Fonte\SVDMPRA\Backup\SVDPMRADataSet12.xsc">
</Event><Event ErrorLevel="0" Project="SVDMPRA" Source="SVDPMRADataSet12.xsd" Description="File successfully backed up as D:\bkp\SVDMPRA\SISTEMA E OUTROS\Codigo Fonte\SVDMPRA\Backup\SVDPMRADataSet12.xsd">
</Event><Event ErrorLevel="0" Project="SVDMPRA" Source="SVDPMRADataSet12.xss" Description="File successfully backed up as D:\bkp\SVDMPRA\SISTEMA E OUTROS\Codigo Fonte\SVDMPRA\Backup\SVDPMRADataSet12.xss">
</Event><Event ErrorLevel="0" Project="SVDMPRA" Source="Resources\marcadortst0001.jpg" Description="File successfully backed up as D:\bkp\SVDMPRA\SISTEMA E OUTROS\Codigo Fonte\SVDMPRA\Backup\Resources\marcadortst0001.jpg">
</Event><Event ErrorLevel="0" Project="SVDMPRA" Source="Resources\marcadortst00011.jpg" Description="File successfully backed up as D:\bkp\SVDMPRA\SISTEMA E OUTROS\Codigo Fonte\SVDMPRA\Backup\Resources\marcadortst00011.jpg">
</Event><Event ErrorLevel="0" Project="SVDMPRA" Source="SVDPMRADataSet13.xsc" Description="File successfully backed up as D:\bkp\SVDMPRA\SISTEMA E OUTROS\Codigo Fonte\SVDMPRA\Backup\SVDPMRADataSet13.xsc">
</Event><Event ErrorLevel="0" Project="SVDMPRA" Source="SVDPMRADataSet13.xsd" Description="File successfully backed up as D:\bkp\SVDMPRA\SISTEMA E OUTROS\Codigo Fonte\SVDMPRA\Backup\SVDPMRADataSet13.xsd">
</Event><Event ErrorLevel="0" Project="SVDMPRA" Source="SVDPMRADataSet13.xss" Description="File successfully backed up as D:\bkp\SVDMPRA\SISTEMA E OUTROS\Codigo Fonte\SVDMPRA\Backup\SVDPMRADataSet13.xss">
</Event><Event ErrorLevel="0" Project="SVDMPRA" Source="Cliente\frmclicon.resx" Description="File successfully backed up as D:\bkp\SVDMPRA\SISTEMA E OUTROS\Codigo Fonte\SVDMPRA\Backup\Cliente\frmclicon.resx">
</Event><Event ErrorLevel="0" Project="SVDMPRA" Source="Cliente\frmclicad.resx" Description="File successfully backed up as D:\bkp\SVDMPRA\SISTEMA E OUTROS\Codigo Fonte\SVDMPRA\Backup\Cliente\frmclicad.resx">
</Event><Event ErrorLevel="0" Project="SVDMPRA" Source="Cliente\frmclimod.resx" Description="File successfully backed up as D:\bkp\SVDMPRA\SISTEMA E OUTROS\Codigo Fonte\SVDMPRA\Backup\Cliente\frmclimod.resx">
</Event><Event ErrorLevel="0" Project="SVDMPRA" Source="Geracao3d\Form1.resx" Description="File successfully backed up as D:\bkp\SVDMPRA\SISTEMA E OUTROS\Codigo Fonte\SVDMPRA\Backup\Geracao3d\Form1.resx">
</Event><Event ErrorLevel="0" Project="SVDMPRA" Source="Geracao3d\Form2.resx" Description="File successfully backed up as D:\bkp\SVDMPRA\SISTEMA E OUTROS\Codigo Fonte\SVDMPRA\Backup\Geracao3d\Form2.resx">
</Event><Event ErrorLevel="0" Project="SVDMPRA" Source="Geracao3d\Form3.resx" Description="File successfully backed up as D:\bkp\SVDMPRA\SISTEMA E OUTROS\Codigo Fonte\SVDMPRA\Backup\Geracao3d\Form3.resx">
</Event><Event ErrorLevel="0" Project="SVDMPRA" Source="Geracao3d\frmnomeset.resx" Description="File successfully backed up as D:\bkp\SVDMPRA\SISTEMA E OUTROS\Codigo Fonte\SVDMPRA\Backup\Geracao3d\frmnomeset.resx">
</Event><Event ErrorLevel="0" Project="SVDMPRA" Source="Imoveis\frmmodimo.resx" Description="File successfully backed up as D:\bkp\SVDMPRA\SISTEMA E OUTROS\Codigo Fonte\SVDMPRA\Backup\Imoveis\frmmodimo.resx">
</Event><Event ErrorLevel="0" Project="SVDMPRA" Source="Imoveis\frmaltim.resx" Description="File successfully backed up as D:\bkp\SVDMPRA\SISTEMA E OUTROS\Codigo Fonte\SVDMPRA\Backup\Imoveis\frmaltim.resx">
</Event><Event ErrorLevel="0" Project="SVDMPRA" Source="Imoveis\frmcadim.resx" Description="File successfully backed up as D:\bkp\SVDMPRA\SISTEMA E OUTROS\Codigo Fonte\SVDMPRA\Backup\Imoveis\frmcadim.resx">
</Event><Event ErrorLevel="0" Project="SVDMPRA" Source="Janela Login\Login.resx" Description="File successfully backed up as D:\bkp\SVDMPRA\SISTEMA E OUTROS\Codigo Fonte\SVDMPRA\Backup\Janela Login\Login.resx">
</Event><Event ErrorLevel="0" Project="SVDMPRA" Source="Marcadores\cadmarc.resx" Description="File successfully backed up as D:\bkp\SVDMPRA\SISTEMA E OUTROS\Codigo Fonte\SVDMPRA\Backup\Marcadores\cadmarc.resx">
</Event><Event ErrorLevel="0" Project="SVDMPRA" Source="Marcadores\consulmark.resx" Description="File successfully backed up as D:\bkp\SVDMPRA\SISTEMA E OUTROS\Codigo Fonte\SVDMPRA\Backup\Marcadores\consulmark.resx">
</Event><Event ErrorLevel="0" Project="SVDMPRA" Source="Menu Principal\principal.resx" Description="File successfully backed up as D:\bkp\SVDMPRA\SISTEMA E OUTROS\Codigo Fonte\SVDMPRA\Backup\Menu Principal\principal.resx">
</Event><Event ErrorLevel="0" Project="SVDMPRA" Source="Móveis\frmcadmov2.resx" Description="File successfully backed up as D:\bkp\SVDMPRA\SISTEMA E OUTROS\Codigo Fonte\SVDMPRA\Backup\Móveis\frmcadmov2.resx">
</Event><Event ErrorLevel="0" Project="SVDMPRA" Source="Móveis\frmmodmov.resx" Description="File successfully backed up as D:\bkp\SVDMPRA\SISTEMA E OUTROS\Codigo Fonte\SVDMPRA\Backup\Móveis\frmmodmov.resx">
</Event><Event ErrorLevel="0" Project="SVDMPRA" Source="Móveis\frmmovcons.resx" Description="File successfully backed up as D:\bkp\SVDMPRA\SISTEMA E OUTROS\Codigo Fonte\SVDMPRA\Backup\Móveis\frmmovcons.resx">
</Event><Event ErrorLevel="0" Project="SVDMPRA" Source="Planta\Frmconpla.resx" Description="File successfully backed up as D:\bkp\SVDMPRA\SISTEMA E OUTROS\Codigo Fonte\SVDMPRA\Backup\Planta\Frmconpla.resx">
</Event><Event ErrorLevel="0" Project="SVDMPRA" Source="Planta\frmmodpla.resx" Description="File successfully backed up as D:\bkp\SVDMPRA\SISTEMA E OUTROS\Codigo Fonte\SVDMPRA\Backup\Planta\frmmodpla.resx">
</Event><Event ErrorLevel="0" Project="SVDMPRA" Source="Planta\frmplancad.resx" Description="File successfully backed up as D:\bkp\SVDMPRA\SISTEMA E OUTROS\Codigo Fonte\SVDMPRA\Backup\Planta\frmplancad.resx">
</Event><Event ErrorLevel="0" Project="SVDMPRA" Source="Properties\licenses.licx" Description="File successfully backed up as D:\bkp\SVDMPRA\SISTEMA E OUTROS\Codigo Fonte\SVDMPRA\Backup\Properties\licenses.licx">
</Event><Event ErrorLevel="0" Project="SVDMPRA" Source="Properties\Resources.resx" Description="File successfully backed up as D:\bkp\SVDMPRA\SISTEMA E OUTROS\Codigo Fonte\SVDMPRA\Backup\Properties\Resources.resx">
</Event><Event ErrorLevel="0" Project="SVDMPRA" Source="SVDMPRA.csproj" Description="Project converted successfully">
</Event><Event ErrorLevel="3" Project="SVDMPRA" Source="SVDMPRA.csproj" Description="Converted">
</Event><Event ErrorLevel="0" Project="" Source="SVDMPRA.sln" Description="Solution converted successfully">
</Event><Event ErrorLevel="3" Project="" Source="SVDMPRA.sln" Description="Converted">
</Event><Event ErrorLevel="0" Project="SVDMPRA" Source="SVDMPRA.csproj" Description="Scan complete: Upgrade not required for project files.">
</Event></UpgradeLog>